lattice/__init__.py
lattice/core.schema.yaml
lattice/docs/__init__.py
lattice/docs/grid_table.py
lattice/docs/hugo_layouts/_default/list.html
lattice/docs/hugo_layouts/_default/single.html
lattice/docs/hugo_layouts/landing/baseof.html
lattice/docs/hugo_layouts/partials/cover.html
lattice/docs/hugo_layouts/partials/page-meta-links.html
lattice/docs/hugo_layouts/specifications/baseof.html
lattice/docs/hugo_layouts/specifications/baseof.print.html
lattice/docs/hugo_layouts/specifications/list.html
lattice/docs/hugo_layouts/specifications/list.print.html
lattice/docs/hugo_layouts/specifications/single.html
lattice/docs/hugo_web.py
lattice/docs/process_template.py
lattice/docs/schema_table.py
lattice/docs/scss_template.scss.j2
lattice/file_io.py
lattice/lattice.py
lattice/meta.schema.yaml
lattice/meta_schema.py
lattice/schema_to_json.py
lattice-0.1.4.dist-info/LICENSE.txt
lattice-0.1.4.dist-info/WHEEL
lattice-0.1.4.dist-info/METADATA
lattice-0.1.4.dist-info/RECORD
