Metadata-Version: 2.1
Name: lattice
Version: 0.1.4
Summary: A framework for developing data models, including schema development and documentation.
Home-page: https://github.com/bigladder/lattice
License: BSD-3
Keywords: data-modeling,schema,lattice
Author: Big Ladder Software
Requires-Python: >=3.7,<4.0
Classifier: License :: Other/Proprietary License
Classifier: Programming Language :: Python :: 3
Classifier: Programming Language :: Python :: 3.7
Classifier: Programming Language :: Python :: 3.8
Classifier: Programming Language :: Python :: 3.9
Classifier: Programming Language :: Python :: 3.10
Classifier: Programming Language :: Python :: 3.11
Requires-Dist: Jinja2
Requires-Dist: cbor2
Requires-Dist: jsonschema
Requires-Dist: pygit2 (>=1.10.0,<2.0.0)
Requires-Dist: pyyaml
Requires-Dist: stringcase (==1.2.0)
Project-URL: Repository, https://github.com/bigladder/lattice
